mac_counter_verilog/_____00003aT0_00003a_00003amy__cnt_00003aT0.v
`timescale 1ps/1ps

module _____00003aT0_00003a_00003amy__cnt_00003aT0( ack, rst, ack__mac ); 
   input ack;
   input rst;
   output reg ack__mac;
   reg [1:0] q;

   always @( posedge rst ) begin

      q <= 32'd0;

      ack__mac <= 32'd0;

   end

   always @( posedge ack ) begin

      q <= (q + 32'd1);

   end

   always @( negedge ack ) begin

      if ((q == 32'd2)) begin
         q <= 32'd0;
      end

   end

   always @( q ) begin

      if ((q == 32'd2)) begin
         ack__mac <= 32'd1;
      end
      else begin
         ack__mac <= 32'd0;
      end

   end

endmodule

mac_counter_verilog/mac_counter.v
`timescale 1ps/1ps

module _____00003aT0( ); 
   reg ack;
   reg rst;
   wire ack__mac;
   wire _00005e_0000600;
   wire _00005e_0000601;
   wire _00005e_0000602;

   _____00003aT0_00003a_00003amy__cnt_00003aT0 my__cnt(.ack(_00005e_0000600),.rst(_00005e_0000601),.ack__mac(_00005e_0000602));
   assign _00005e_0000600 = ack;

   assign _00005e_0000601 = rst;

   assign ack__mac = _00005e_0000602;

   initial begin

      rst = 32'd0;

      ack = 32'd0;

      #5

      rst = 32'd1;

      #5

      ack = 32'd1;

      #5

      ack = 32'd0;

      #5

      ack = 32'd1;

      #5

      ack = 32'd0;

      #5

      ack = 32'd1;

      #5

      ack = 32'd0;

      #5

      ack = 32'd1;

      #5

      ack = 32'd0;

      #5

      ack = 32'd1;

      #5

      ack = 32'd0;

      #5

      ack = 32'd1;

      #5

      ack = 32'd0;

      #5

      ack = 32'd1;

      #5

      ack = 32'd0;

      #5

      ack = 32'd1;

      #5

      ack = 32'd0;

      #5

      ack = 32'd1;

      #5

      ack = 32'd0;

      #5

      ack = 32'd1;

      #5

      ack = 32'd0;

      #5

      $finish;
   end

   initial begin
      $dumpfile("mac.vcd");
      $dumpvars(0, _____00003aT0);
   end

endmodule

mac_counter_verilog/mac.vcd
$date
	Fri Sep 11 01:42:29 2020
$end
$version
	Icarus Verilog
$end
$timescale
	1ps
$end
$scope module _____00003aT0 $end
$var wire 1 ! _00005e_0000600 $end
$var wire 1 " _00005e_0000601 $end
$var wire 1 # ack__mac $end
$var wire 1 $ _00005e_0000602 $end
$var reg 1 % ack $end
$var reg 1 & rst $end
$scope module my__cnt $end
$var wire 1 ! ack $end
$var wire 1 " rst $end
$var reg 1 $ ack__mac $end
$var reg 2 ' q [1:0] $end
$upscope $end
$upscope $end
$enddefinitions $end
#0
$dumpvars
bx '
0&
0%
x$
x#
0"
0!
$end
#5
0#
0$
b0 '
1"
1&
#10
b1 '
1!
1%
#15
0!
0%
#20
1#
1$
b10 '
1!
1%
#25
0#
0$
b0 '
0!
0%
#30
b1 '
1!
1%
#35
0!
0%
#40
1#
1$
b10 '
1!
1%
#45
0#
0$
b0 '
0!
0%
#50
b1 '
1!
1%
#55
0!
0%
#60
1#
1$
b10 '
1!
1%
#65
0#
0$
b0 '
0!
0%
#70
b1 '
1!
1%
#75
0!
0%
#80
1#
1$
b10 '
1!
1%
#85
0#
0$
b0 '
0!
0%
#90
b1 '
1!
1%
#95
0!
0%
#100
1#
1$
b10 '
1!
1%
#105
0#
0$
b0 '
0!
0%
